codx/__init__.py
codx/cli.py
codx/components.py
codx/test_cli.py
codx/test_components.py
codx-0.1.3.dist-info/entry_points.txt
codx-0.1.3.dist-info/LICENSE
codx-0.1.3.dist-info/METADATA
codx-0.1.3.dist-info/WHEEL
codx-0.1.3.dist-info/RECORD
