Metadata-Version: 2.1
Name: codx
Version: 0.1.3
Summary: A package used to retrieve exon for protein sequences from RefSeqGene database
License: MIT
Author: Toan Phung
Author-email: toan.phungkhoiquoctoan@gmail.com
Requires-Python: >=3.9,<4.0
Classifier: License :: OSI Approved :: MIT License
Classifier: Programming Language :: Python :: 3
Classifier: Programming Language :: Python :: 3.9
Classifier: Programming Language :: Python :: 3.10
Classifier: Programming Language :: Python :: 3.11
Classifier: Programming Language :: Python :: 3.12
Requires-Dist: biopython (>=1.81,<2.0)
Requires-Dist: click (>=8.1.3,<9.0.0)
Requires-Dist: django-admin-tools (>=0.9.3,<0.10.0)
Requires-Dist: pandas (>=2.2.2,<3.0.0)
Requires-Dist: uniprotparser (>=1.0.9,<2.0.0)
